pySearchErr/__init__.py
pySearchErr-0.1.3.data/scripts/pySearchErr
pySearchErr-0.1.3.dist-info/METADATA
pySearchErr-0.1.3.dist-info/WHEEL
pySearchErr-0.1.3.dist-info/top_level.txt
pySearchErr-0.1.3.dist-info/RECORD
