Metadata-Version: 2.1
Name: pySearchErr
Version: 0.1.3
Summary: Detects Python3 exception and searches for the error on Google automatically
Home-page: https://github.com/JING1201/SwampHacks2020
Author: jlionwg
License: MIT
Platform: UNKNOWN
